{
  "success": true,
  "count": 15,
  "relays_searched": 4,
  "servers": [
    "https://blssm.us/",
    "https://blossom.azzamo.media/",
    "https://cdn.nostrcheck.me/",
    "https://blossom.yakihonne.com/",
    "https://blossom-02.uid.ovh/",
    "https://blossom-01.uid.ovh/",
    "https://blossom.sector01.com/",
    "https://blossom.band/",
    "https://24242.io/",
    "https://cdn.sovbit.host/",
    "https://loratu.bitcointxoko.com/",
    "https://otherstuff.shaving.kiwi/",
    "https://cdn.hzrd149.com/",
    "https://blossom.nostr.hu/",
    "https://nostr.download/"
  ],
  "timestamp": "2026-04-26T05:00:22.463Z"
}